eea_pkg/__init__.py
zk_eea-1.0.0.dist-info/LICENSE
zk_eea-1.0.0.dist-info/METADATA
zk_eea-1.0.0.dist-info/WHEEL
zk_eea-1.0.0.dist-info/top_level.txt
zk_eea-1.0.0.dist-info/RECORD
