Metadata-Version: 2.1
Name: zk-eea
Version: 1.0.0
Summary: Extended Euclidean Algorithm
Home-page: https://github.com/zlhwdsz/eea
Author: He Weidong
Author-email: zlhwd@qq.com
Classifier: Programming Language :: Python :: 3
Classifier: License :: OSI Approved :: MIT License
Classifier: Operating System :: OS Independent
Requires-Python: >=3.6
License-File: LICENSE
